tool_kit/__init__.py
tool_kit/base_widgets.py
tool_kit/category_detail_widget.py
tool_kit/category_list_widget.py
tool_kit/common_class.py
tool_kit/main.py
tool_kit/register.py
tool_kit/settingsbase.py
tool_kit/summary_widget.py
tool_kit/tool_config.py
simple_tool_kit_ui-0.0.5.dist-info/METADATA
simple_tool_kit_ui-0.0.5.dist-info/WHEEL
simple_tool_kit_ui-0.0.5.dist-info/top_level.txt
simple_tool_kit_ui-0.0.5.dist-info/RECORD
