Metadata-Version: 2.1
Name: simple-tool-kit-ui
Version: 0.0.5
Summary: simple tool kit
Author-email: qiao <narutozbjp@hotmail.com>
Classifier: Development Status :: 4 - Beta
Classifier: Programming Language :: Python
Requires-Python: >=3.8
